lapymod/__init__.py
lapymod/configs/__init__.py
lapymod/configs/cosmetics.json
lapymod/configs/emotes.json
lapymod/configs/roles.json
lapymod/configs/stickers.json
lapymod/utils/__init__.py
lapymod/utils/humanize.py
lapymod/utils/labymod.py
lapymod/utils/user.py
lapymod-1.1.dist-info/LICENSE
lapymod-1.1.dist-info/METADATA
lapymod-1.1.dist-info/WHEEL
lapymod-1.1.dist-info/top_level.txt
lapymod-1.1.dist-info/RECORD
