Metadata-Version: 2.1
Name: lapymod
Version: 1.1
Summary: A simple wrapper for Labymod's API.
Home-page: https://github.com/lag/lapymod
Author: Lag
Author-email: no@email.com
License: UNKNOWN
Platform: UNKNOWN
Classifier: Programming Language :: Python :: 3
Classifier: License :: OSI Approved :: MIT License
Classifier: Operating System :: OS Independent
Requires-Python: >=3.6
